Metadata-Version: 1.0
Name: jo-story
Version: 0.1
Summary: story about jo
Home-page: UNKNOWN
Author: John Lhota
Author-email: johnlhota@example.com
License: MIT
Platform: UNKNOWN
